{"type":"Scene","props":{"width":487.75,"height":380},"compId":2,"child":[{"type":"Box","props":{"y":159,"width":487.75,"var":"box_ship","scaleX":1,"height":260,"centerX":0,"anchorY":0.5,"anchorX":0.5},"compId":15,"child":[{"type":"Image","props":{"y":-93,"x":135.875,"width":8,"skin":"resource/assets/img/game/boat_q1_hp_holder.png","rotation":0,"height":256},"compId":95},{"type":"Box","props":{"y":-121,"x":143.875,"width":100,"var":"box_blood","height":50},"compId":74},{"type":"Box","props":{"y":163,"x":243.875,"width":500,"var":"box_ui","height":333,"anchorY":0.5,"anchorX":0.5},"compId":53,"child":[{"type":"Box","props":{"y":-31,"x":277,"width":113,"var":"box1","scaleY":0.4,"scaleX":0.4,"height":256},"compId":24},{"type":"Box","props":{"y":9,"x":-12,"width":484,"var":"behind","height":217},"compId":16,"child":[{"type":"Sprite","props":{"y":-52,"x":188,"width":62,"texture":"resource/assets/img/game/ship/110103/boat_q3_sail.png","rotation":-66,"height":322},"compId":94},{"type":"Sprite","props":{"y":-91,"x":109,"width":97,"texture":"resource/assets/img/game/ship/110103/boat_q3_hp_holder.png","height":308},"compId":89}]},{"type":"Box","props":{"y":61,"x":15,"width":485,"var":"middle","height":255},"compId":17,"child":[{"type":"Box","props":{"y":38,"x":376,"width":100,"var":"box_player3","scaleY":0.8,"scaleX":0.8,"height":150,"anchorY":0.5,"anchorX":0.5},"compId":29,"child":[{"type":"Image","props":{"y":71,"x":0,"width":100,"skin":"resource/assets/img/game/ship/cat_capsule.png","sizeGrid":"0,0,0,0","name":"solt","height":81,"centerX":0},"compId":76}]},{"type":"Box","props":{"y":27,"x":258,"width":100,"var":"box_player1","scaleY":0.8,"scaleX":0.8,"height":150,"anchorY":0.5,"anchorX":0.5},"compId":25,"child":[{"type":"Image","props":{"y":158,"width":100,"skin":"resource/assets/img/game/ship/cat_capsule.png","sizeGrid":"0,0,0,0","scaleY":-1,"name":"solt","height":81,"centerX":0},"compId":77}]},{"type":"Box","props":{"y":38,"x":138,"width":100,"var":"box_player2","scaleY":0.8,"scaleX":0.8,"height":150,"anchorY":0.5,"anchorX":0.5},"compId":27,"child":[{"type":"Image","props":{"y":71,"x":0,"width":100,"skin":"resource/assets/img/game/ship/cat_capsule.png","sizeGrid":"0,0,0,0","name":"solt","height":81,"centerX":0},"compId":78}]},{"type":"Box","props":{"y":200,"x":368,"width":100,"var":"box_player5","scaleY":-1,"mouseThrough":true,"height":150,"anchorY":0.5,"anchorX":0.5},"compId":44,"child":[{"type":"Image","props":{"y":71,"x":0,"width":100,"skin":"resource/assets/img/game/ship/cat_capsule.png","sizeGrid":"0,0,0,0","name":"solt","height":81,"centerX":0},"compId":79}]},{"type":"Box","props":{"y":200,"x":227,"width":100,"var":"box_player4","scaleY":-1,"height":150,"anchorY":0.5,"anchorX":0.5},"compId":45,"child":[{"type":"Image","props":{"y":71,"x":0,"width":100,"skin":"resource/assets/img/game/ship/cat_capsule.png","sizeGrid":"0,0,0,0","name":"solt","height":81,"centerX":0},"compId":80}]}]},{"type":"Box","props":{"y":9,"x":-12,"width":497,"var":"front","mouseThrough":true,"mouseEnabled":false,"height":216},"compId":18,"child":[{"type":"Sprite","props":{"y":71,"x":89,"width":462,"texture":"resource/assets/img/game/ship/110103/boat_q3_hull.png","height":165},"compId":88},{"type":"Sprite","props":{"y":217,"x":150,"width":46,"texture":"resource/assets/img/game/ship/110103/boat_q3_trumpet.png","height":66},"compId":91},{"type":"Sprite","props":{"y":127,"x":-8,"width":134,"texture":"resource/assets/img/game/ship/110103/boat_q3_engine.png","height":143},"compId":90},{"type":"Sprite","props":{"y":251,"x":50,"width":53,"texture":"resource/assets/img/game/ship/110103/boat_q3_propeller.png","rotation":-12,"height":64},"compId":92},{"type":"Sprite","props":{"y":102,"x":271,"width":189,"texture":"resource/assets/img/game/ship/110103/boat_q3_rope.png","height":76},"compId":93},{"type":"Sprite","props":{"y":178,"x":345,"width":63,"texture":"resource/assets/img/game/ship/copter_q2_porthole.png","height":58},"compId":96}]},{"type":"Image","props":{"y":80,"x":-12,"width":82,"var":"icon_booster","skin":"resource/assets/img/game/booster/hull_shield_generator.png","rotation":-24,"height":154,"anchorY":0.5,"anchorX":0.5},"compId":72}]}]},{"type":"Box","props":{"y":72,"x":0,"width":487.75,"var":"icon_ship","styleSkin":"","height":216.75},"compId":7,"child":[{"type":"Script","props":{"type":"kinematic","bullet":true,"runtime":"laya.physics.RigidBody"},"compId":9},{"type":"Script","props":{"y":0,"x":0,"points":"-15,83,525,68,468,139,419,198,157,206,2,201","runtime":"laya.physics.PolygonCollider"},"compId":47}]},{"type":"Box","props":{"y":153,"x":17,"width":470,"var":"box_detail","height":119},"compId":81},{"type":"Box","props":{"y":53,"x":216,"width":100,"var":"box_col1","height":100},"compId":54,"child":[{"type":"Script","props":{"y":0,"x":0,"width":100,"height":100,"runtime":"laya.physics.BoxCollider"},"compId":62},{"type":"Script","props":{"y":0,"x":0,"type":"kinematic","runtime":"laya.physics.RigidBody"},"compId":63}]},{"type":"Box","props":{"y":53,"x":93,"width":100,"var":"box_col2","height":100},"compId":55,"child":[{"type":"Script","props":{"y":0,"x":0,"width":100,"height":100,"runtime":"laya.physics.BoxCollider"},"compId":64},{"type":"Script","props":{"y":0,"x":0,"type":"kinematic","runtime":"laya.physics.RigidBody"},"compId":65}]},{"type":"Box","props":{"y":44,"x":336,"width":100,"var":"box_col3","height":100},"compId":56,"child":[{"type":"Script","props":{"y":0,"x":0,"width":100,"height":100,"runtime":"laya.physics.BoxCollider"},"compId":66},{"type":"Script","props":{"y":0,"x":0,"type":"kinematic","runtime":"laya.physics.RigidBody"},"compId":67}]},{"type":"Box","props":{"y":222,"x":194,"width":100,"var":"box_col4","height":100},"compId":57,"child":[{"type":"Script","props":{"y":0,"x":0,"width":100,"height":150,"runtime":"laya.physics.BoxCollider"},"compId":68},{"type":"Script","props":{"y":0,"x":0,"type":"kinematic","runtime":"laya.physics.RigidBody"},"compId":69}]},{"type":"Box","props":{"y":222,"x":328,"width":100,"var":"box_col5","mouseThrough":true,"height":100},"compId":58,"child":[{"type":"Script","props":{"y":0,"x":0,"width":100,"height":150,"runtime":"laya.physics.BoxCollider"},"compId":70},{"type":"Script","props":{"y":0,"x":0,"type":"kinematic","runtime":"laya.physics.RigidBody"},"compId":71}]}],"loadList":["resource/assets/img/game/boat_q1_hp_holder.png","resource/assets/img/game/ship/110103/boat_q3_sail.png","resource/assets/img/game/ship/110103/boat_q3_hp_holder.png","resource/assets/img/game/ship/cat_capsule.png","resource/assets/img/game/ship/110103/boat_q3_hull.png","resource/assets/img/game/ship/110103/boat_q3_trumpet.png","resource/assets/img/game/ship/110103/boat_q3_engine.png","resource/assets/img/game/ship/110103/boat_q3_propeller.png","resource/assets/img/game/ship/110103/boat_q3_rope.png","resource/assets/img/game/ship/copter_q2_porthole.png","resource/assets/img/game/booster/hull_shield_generator.png"],"loadList3D":[]}