{"type":"Scene","props":{"width":487.75,"height":380},"compId":2,"child":[{"type":"Box","props":{"y":159,"width":487.75,"var":"box_ship","height":260,"centerX":0,"anchorY":0.5,"anchorX":0.5},"compId":15,"child":[{"type":"Box","props":{"y":-132,"x":72,"width":100,"var":"box_blood","height":50},"compId":74},{"type":"Box","props":{"y":163,"x":243.875,"width":500,"var":"box_ui","height":333,"anchorY":0.5,"anchorX":0.5},"compId":53,"child":[{"type":"Box","props":{"y":-31,"x":277,"width":113,"var":"box1","scaleY":0.4,"scaleX":0.4,"height":256},"compId":24},{"type":"Box","props":{"y":9,"x":-12,"width":484,"var":"behind","height":217},"compId":16,"child":[{"type":"Sprite","props":{"y":-137,"x":82,"width":13,"texture":"resource/assets/img/game/ship/110102/boat_q2_awning_holder.png","height":196},"compId":85},{"type":"Sprite","props":{"y":-58,"x":-46,"texture":"resource/assets/img/game/ship/110102/boat_q2_awning.png"},"compId":86},{"type":"Sprite","props":{"y":22,"x":17,"width":116,"texture":"resource/assets/img/game/ship/110102/boat_q2_balloon_fragment.png","height":118},"compId":84}]},{"type":"Box","props":{"y":61,"x":15,"width":485,"var":"middle","height":255},"compId":17,"child":[{"type":"Box","props":{"y":38,"x":390,"width":100,"var":"box_player3","height":150,"anchorY":0.5,"anchorX":0.5},"compId":29,"child":[{"type":"Image","props":{"y":71,"x":0,"width":100,"skin":"resource/assets/img/game/ship/cat_capsule.png","sizeGrid":"0,0,0,0","name":"solt","height":81,"centerX":0},"compId":76}]},{"type":"Box","props":{"y":38,"x":238,"width":100,"var":"box_player1","height":150,"anchorY":0.5,"anchorX":0.5},"compId":25,"child":[{"type":"Image","props":{"y":158,"width":100,"skin":"resource/assets/img/game/ship/cat_capsule.png","sizeGrid":"0,0,0,0","scaleY":-1,"name":"solt","height":81,"centerX":0},"compId":77}]},{"type":"Box","props":{"y":38,"x":119,"width":100,"var":"box_player2","height":150,"anchorY":0.5,"anchorX":0.5},"compId":27,"child":[{"type":"Image","props":{"y":71,"x":0,"width":100,"skin":"resource/assets/img/game/ship/cat_capsule.png","sizeGrid":"0,0,0,0","name":"solt","height":81,"centerX":0},"compId":78}]},{"type":"Box","props":{"y":207,"x":390,"width":100,"var":"box_player5","scaleY":-1,"mouseThrough":true,"height":150,"anchorY":0.5,"anchorX":0.5},"compId":44,"child":[{"type":"Image","props":{"y":71,"x":0,"width":100,"skin":"resource/assets/img/game/ship/cat_capsule.png","sizeGrid":"0,0,0,0","name":"solt","height":81,"centerX":0},"compId":79}]},{"type":"Box","props":{"y":215,"x":238,"width":100,"var":"box_player4","scaleY":-1,"height":150,"anchorY":0.5,"anchorX":0.5},"compId":45,"child":[{"type":"Image","props":{"y":71,"x":0,"width":100,"skin":"resource/assets/img/game/ship/cat_capsule.png","sizeGrid":"0,0,0,0","name":"solt","height":81,"centerX":0},"compId":80}]}]},{"type":"Box","props":{"y":9,"x":-12,"width":497,"var":"front","mouseThrough":true,"mouseEnabled":false,"height":216},"compId":18,"child":[{"type":"Sprite","props":{"y":100,"x":0,"width":510,"texture":"resource/assets/img/game/ship/110102/boat_q2_hull_boat.png","height":157},"compId":83},{"type":"Sprite","props":{"y":158,"x":381,"width":63,"texture":"resource/assets/img/game/ship/copter_q2_porthole.png","height":58},"compId":87}]},{"type":"Image","props":{"y":256.2,"x":47,"width":81.6,"var":"icon_booster","skin":"resource/assets/img/game/booster/hull_shield_generator.png","scaleY":-1,"height":153.6,"anchorY":0.5,"anchorX":0.5},"compId":72}]}]},{"type":"Box","props":{"y":72,"x":0,"width":487.75,"var":"icon_ship","styleSkin":"","height":216.75},"compId":7,"child":[{"type":"Script","props":{"type":"kinematic","bullet":true,"runtime":"laya.physics.RigidBody"},"compId":9},{"type":"Script","props":{"y":0,"x":0,"points":"38,68,500,86,468,139,426,203,157,206,52,128","runtime":"laya.physics.PolygonCollider"},"compId":47}]},{"type":"Box","props":{"y":153.5,"x":9,"width":470,"var":"box_detail","height":119},"compId":81},{"type":"Box","props":{"y":32,"x":202,"width":100,"var":"box_col1","height":100},"compId":54,"child":[{"type":"Script","props":{"y":0,"x":0,"width":100,"height":100,"runtime":"laya.physics.BoxCollider"},"compId":62},{"type":"Script","props":{"y":0,"x":0,"type":"kinematic","runtime":"laya.physics.RigidBody"},"compId":63}]},{"type":"Box","props":{"y":44,"x":79,"width":100,"var":"box_col2","height":100},"compId":55,"child":[{"type":"Script","props":{"y":0,"x":0,"width":100,"height":100,"runtime":"laya.physics.BoxCollider"},"compId":64},{"type":"Script","props":{"y":0,"x":0,"type":"kinematic","runtime":"laya.physics.RigidBody"},"compId":65}]},{"type":"Box","props":{"y":44,"x":349,"width":100,"var":"box_col3","height":100},"compId":56,"child":[{"type":"Script","props":{"y":0,"x":0,"width":100,"height":100,"runtime":"laya.physics.BoxCollider"},"compId":66},{"type":"Script","props":{"y":0,"x":0,"type":"kinematic","runtime":"laya.physics.RigidBody"},"compId":67}]},{"type":"Box","props":{"y":213,"x":193,"width":100,"var":"box_col4","height":100},"compId":57,"child":[{"type":"Script","props":{"y":0,"x":0,"width":100,"height":150,"runtime":"laya.physics.BoxCollider"},"compId":68},{"type":"Script","props":{"y":0,"x":0,"type":"kinematic","runtime":"laya.physics.RigidBody"},"compId":69}]},{"type":"Box","props":{"y":213,"x":349,"width":100,"var":"box_col5","mouseThrough":true,"height":100},"compId":58,"child":[{"type":"Script","props":{"y":0,"x":0,"width":100,"height":150,"runtime":"laya.physics.BoxCollider"},"compId":70},{"type":"Script","props":{"y":0,"x":0,"type":"kinematic","runtime":"laya.physics.RigidBody"},"compId":71}]}],"loadList":["resource/assets/img/game/ship/110102/boat_q2_awning_holder.png","resource/assets/img/game/ship/110102/boat_q2_awning.png","resource/assets/img/game/ship/110102/boat_q2_balloon_fragment.png","resource/assets/img/game/ship/cat_capsule.png","resource/assets/img/game/ship/110102/boat_q2_hull_boat.png","resource/assets/img/game/ship/copter_q2_porthole.png","resource/assets/img/game/booster/hull_shield_generator.png"],"loadList3D":[]}