{"frames":{"bk_dot.png":{"frame":{"h":42,"idx":0,"w":42,"x":468,"y":382},"sourceSize":{"h":42,"w":42},"spriteSourceSize":{"x":0,"y":0}},"bk_icon_db.png":{"frame":{"h":176,"idx":0,"w":176,"x":414,"y":0},"sourceSize":{"h":176,"w":176},"spriteSourceSize":{"x":0,"y":0}},"bk_icon_mask.png":{"frame":{"h":201,"idx":0,"w":203,"x":0,"y":258},"sourceSize":{"h":201,"w":203},"spriteSourceSize":{"x":0,"y":0}},"gl_icon_2.png":{"frame":{"h":172,"idx":0,"w":172,"x":205,"y":160},"sourceSize":{"h":172,"w":172},"spriteSourceSize":{"x":0,"y":0}},"icon-2.png":{"frame":{"h":159,"idx":0,"w":208,"x":205,"y":0},"sourceSize":{"h":159,"w":208},"spriteSourceSize":{"x":0,"y":0}},"icon.png":{"frame":{"h":67,"idx":0,"w":74,"x":591,"y":0},"sourceSize":{"h":67,"w":74},"spriteSourceSize":{"x":0,"y":0}},"kaishiluzhi.png":{"frame":{"h":54,"idx":0,"w":346,"x":378,"y":288},"sourceSize":{"h":54,"w":346},"spriteSourceSize":{"x":0,"y":0}},"luzhizhong.png":{"frame":{"h":55,"idx":0,"w":353,"x":378,"y":177},"sourceSize":{"h":55,"w":353},"spriteSourceSize":{"x":0,"y":0}},"show1.png":{"frame":{"h":55,"idx":0,"w":263,"x":204,"y":382},"sourceSize":{"h":55,"w":263},"spriteSourceSize":{"x":0,"y":0}},"tt_box_db.png":{"frame":{"h":257,"idx":0,"w":204,"x":0,"y":0},"sourceSize":{"h":257,"w":204},"spriteSourceSize":{"x":0,"y":0}},"videodouble.png":{"frame":{"h":54,"idx":0,"w":356,"x":378,"y":233},"sourceSize":{"h":54,"w":356},"spriteSourceSize":{"x":0,"y":0}},"zi-1.png":{"frame":{"h":56,"idx":0,"w":211,"x":204,"y":438},"sourceSize":{"h":56,"w":211},"spriteSourceSize":{"x":0,"y":0}},"zi-2.png":{"frame":{"h":38,"idx":0,"w":437,"x":204,"y":343},"sourceSize":{"h":38,"w":437},"spriteSourceSize":{"x":0,"y":0}}},"meta":{"image":"tt.png","prefix":"resource/assets/img/tt/"}}