[
{"id":"140001","name":"3倍射击","star":"1","effectID":"1","type":"1","value":"0","needPlayerLevel":"1","icon":"gadget_bandolier_multi|gadget_button_multi","des":"激活后每只猫的下一次攻击变为3发子弹","uiIcon":"boosterIcon_multi"},
{"id":"140002","name":"3倍射击","star":"2","effectID":"1","type":"1","value":"0","needPlayerLevel":"2","icon":"gadget_bandolier_multi|gadget_button_multi","des":"激活后每只猫的下一次攻击变为3发子弹","uiIcon":"boosterIcon_multi"},
{"id":"140003","name":"3倍射击","star":"3","effectID":"1","type":"1","value":"0","needPlayerLevel":"3","icon":"gadget_bandolier_multi|gadget_button_multi","des":"激活后每只猫的下一次攻击变为3发子弹","uiIcon":"boosterIcon_multi"},
{"id":"140004","name":"3倍射击","star":"4","effectID":"1","type":"1","value":"0","needPlayerLevel":"4","icon":"gadget_bandolier_multi|gadget_button_multi","des":"激活后每只猫的下一次攻击变为3发子弹","uiIcon":"boosterIcon_multi"},
{"id":"140005","name":"3倍射击","star":"5","effectID":"1","type":"1","value":"0","needPlayerLevel":"5","icon":"gadget_bandolier_multi|gadget_button_multi","des":"激活后每只猫的下一次攻击变为3发子弹","uiIcon":"boosterIcon_multi"},
{"id":"140101","name":"穿甲弹","star":"1","effectID":"2","type":"2","value":"0","needPlayerLevel":"3","icon":"gadget_bandolier_piercing|gadget_button_piercing","des":"激活后每只猫的下一次攻击无视敌方护盾","uiIcon":"boosterIcon_piercing"},
{"id":"140102","name":"穿甲弹","star":"2","effectID":"2","type":"2","value":"0","needPlayerLevel":"3","icon":"gadget_bandolier_piercing|gadget_button_piercing","des":"激活后每只猫的下一次攻击无视敌方护盾","uiIcon":"boosterIcon_piercing"},
{"id":"140103","name":"穿甲弹","star":"3","effectID":"2","type":"2","value":"0","needPlayerLevel":"3","icon":"gadget_bandolier_piercing|gadget_button_piercing","des":"激活后每只猫的下一次攻击无视敌方护盾","uiIcon":"boosterIcon_piercing"},
{"id":"140104","name":"穿甲弹","star":"4","effectID":"2","type":"2","value":"0","needPlayerLevel":"4","icon":"gadget_bandolier_piercing|gadget_button_piercing","des":"激活后每只猫的下一次攻击无视敌方护盾","uiIcon":"boosterIcon_piercing"},
{"id":"140105","name":"穿甲弹","star":"5","effectID":"2","type":"2","value":"0","needPlayerLevel":"5","icon":"gadget_bandolier_piercing|gadget_button_piercing","des":"激活后每只猫的下一次攻击无视敌方护盾","uiIcon":"boosterIcon_piercing"},
{"id":"140201","name":"猪猪支援M1","star":"1","effectID":"3","type":"3","value":"140201","needPlayerLevel":"0","icon":"gadget_piggenerator_mk1|gadget_button_mk1","des":"召唤1只飞天猪猪反抗军为你作战","uiIcon":"boosterIcon_piggenerator_mk1"},
{"id":"140202","name":"猪猪支援M1","star":"2","effectID":"3","type":"3","value":"140202","needPlayerLevel":"0","icon":"gadget_piggenerator_mk1|gadget_button_mk1","des":"召唤1只飞天猪猪反抗军为你作战","uiIcon":"boosterIcon_piggenerator_mk1"},
{"id":"140203","name":"猪猪支援M1","star":"3","effectID":"3","type":"3","value":"140203","needPlayerLevel":"0","icon":"gadget_piggenerator_mk1|gadget_button_mk1","des":"召唤1只飞天猪猪反抗军为你作战","uiIcon":"boosterIcon_piggenerator_mk1"},
{"id":"140204","name":"猪猪支援M1","star":"4","effectID":"3","type":"3","value":"140204","needPlayerLevel":"0","icon":"gadget_piggenerator_mk1|gadget_button_mk1","des":"召唤1只飞天猪猪反抗军为你作战","uiIcon":"boosterIcon_piggenerator_mk1"},
{"id":"140205","name":"猪猪支援M1","star":"5","effectID":"3","type":"3","value":"140205","needPlayerLevel":"0","icon":"gadget_piggenerator_mk1|gadget_button_mk1","des":"召唤1只飞天猪猪反抗军为你作战","uiIcon":"boosterIcon_piggenerator_mk1"},
{"id":"140301","name":"猪猪支援M2","star":"1","effectID":"4","type":"4","value":"140301","needPlayerLevel":"2","icon":"gadget_piggenerator_mk2|gadget_button_mk2","des":"召唤1只潜水猪猪反抗军为你作战","uiIcon":"boosterIcon_piggenerator_mk2"},
{"id":"140302","name":"猪猪支援M2","star":"2","effectID":"4","type":"4","value":"140302","needPlayerLevel":"2","icon":"gadget_piggenerator_mk2|gadget_button_mk2","des":"召唤1只潜水猪猪反抗军为你作战","uiIcon":"boosterIcon_piggenerator_mk2"},
{"id":"140303","name":"猪猪支援M2","star":"3","effectID":"4","type":"4","value":"140303","needPlayerLevel":"3","icon":"gadget_piggenerator_mk2|gadget_button_mk2","des":"召唤1只潜水猪猪反抗军为你作战","uiIcon":"boosterIcon_piggenerator_mk2"},
{"id":"140304","name":"猪猪支援M2","star":"4","effectID":"4","type":"4","value":"140304","needPlayerLevel":"4","icon":"gadget_piggenerator_mk2|gadget_button_mk2","des":"召唤1只潜水猪猪反抗军为你作战","uiIcon":"boosterIcon_piggenerator_mk2"},
{"id":"140305","name":"猪猪支援M2","star":"5","effectID":"4","type":"4","value":"140305","needPlayerLevel":"5","icon":"gadget_piggenerator_mk2|gadget_button_mk2","des":"召唤1只潜水猪猪反抗军为你作战","uiIcon":"boosterIcon_piggenerator_mk2"},
{"id":"140401","name":"治疗","star":"1","effectID":"5","type":"5","value":"0.25","needPlayerLevel":"4","icon":"gadget_piggenerator_doctor|gadget_button_doctor","des":"治疗血量最低的单位","uiIcon":"boosterIcon_piggenerator_doctor"},
{"id":"140402","name":"治疗","star":"2","effectID":"5","type":"5","value":"0.25","needPlayerLevel":"4","icon":"gadget_piggenerator_doctor|gadget_button_doctor","des":"治疗血量最低的单位","uiIcon":"boosterIcon_piggenerator_doctor"},
{"id":"140403","name":"治疗","star":"3","effectID":"5","type":"5","value":"0.25","needPlayerLevel":"4","icon":"gadget_piggenerator_doctor|gadget_button_doctor","des":"治疗血量最低的单位","uiIcon":"boosterIcon_piggenerator_doctor"},
{"id":"140404","name":"治疗","star":"4","effectID":"5","type":"5","value":"0.25","needPlayerLevel":"4","icon":"gadget_piggenerator_doctor|gadget_button_doctor","des":"治疗血量最低的单位","uiIcon":"boosterIcon_piggenerator_doctor"},
{"id":"140405","name":"治疗","star":"5","effectID":"5","type":"5","value":"0.25","needPlayerLevel":"5","icon":"gadget_piggenerator_doctor|gadget_button_doctor","des":"治疗血量最低的单位","uiIcon":"boosterIcon_piggenerator_doctor"},
{"id":"149901","name":"护盾","star":"1","effectID":"99","type":"99","value":"2500","needPlayerLevel":"0","icon":"hull_shield_generator|gadget_button_doctor","des":"主舰获得一个可以抵消伤害的护盾","uiIcon":""},
{"id":"149902","name":"护盾","star":"2","effectID":"99","type":"99","value":"2500","needPlayerLevel":"0","icon":"hull_shield_generator|gadget_button_doctor","des":"主舰获得一个可以抵消伤害的护盾","uiIcon":""},
{"id":"149903","name":"护盾","star":"3","effectID":"99","type":"99","value":"2500","needPlayerLevel":"0","icon":"hull_shield_generator|gadget_button_doctor","des":"主舰获得一个可以抵消伤害的护盾","uiIcon":""},
{"id":"149904","name":"护盾","star":"4","effectID":"99","type":"99","value":"2500","needPlayerLevel":"0","icon":"hull_shield_generator|gadget_button_doctor","des":"主舰获得一个可以抵消伤害的护盾","uiIcon":""},
{"id":"149905","name":"护盾","star":"5","effectID":"99","type":"99","value":"2500","needPlayerLevel":"0","icon":"hull_shield_generator|gadget_button_doctor","des":"主舰获得一个可以抵消伤害的护盾","uiIcon":""}
]